jsonlf/__main__.py
jsonlf/main.py
jsonlf-0.1.3.dist-info/METADATA
jsonlf-0.1.3.dist-info/entry_points.txt
jsonlf-0.1.3.dist-info/WHEEL
jsonlf-0.1.3.dist-info/LICENSE.md
jsonlf-0.1.3.dist-info/RECORD
