Metadata-Version: 2.1
Name: jsonlf
Version: 0.1.3
Summary: Pretty print a stream of json lines. You can pipe any command that is logging jsonl into this. If the line is not a json it will print as it is.
License: MIT
Author: Matheus Fillipe
Author-email: matheusfillipeag@gmail.com
Requires-Python: >=3.10,<4.0
Classifier: License :: OSI Approved :: MIT License
Classifier: Programming Language :: Python :: 3
Classifier: Programming Language :: Python :: 3.10
Classifier: Programming Language :: Python :: 3.11
Requires-Dist: Pygments (>=2.14.0,<3.0.0)
